LICENSE
pvt100/__init__.py
pvt100-0.1.5.dist-info/LICENSE
pvt100-0.1.5.dist-info/WHEEL
pvt100-0.1.5.dist-info/METADATA
pvt100-0.1.5.dist-info/RECORD
