Metadata-Version: 2.1
Name: pvt100
Version: 0.1.5
Summary: VT100 terminal escape codes for Python
Home-page: https://github.com/SinaKhalili/pvt100
License: MIT
Keywords: vt100,terminal,escape,codes
Author: sina
Author-email: khalili@sfu.ca
Requires-Python: >=3.11,<4.0
Classifier: Development Status :: 3 - Alpha
Classifier: Intended Audience :: Developers
Classifier: License :: OSI Approved :: MIT License
Classifier: Operating System :: OS Independent
Classifier: Programming Language :: Python :: 3
Classifier: Programming Language :: Python :: 3.11
Project-URL: Repository, https://github.com/SinaKhalili/pvt100
